setup.py
chushajo/__init__.py
chushajo.egg-info/PKG-INFO
chushajo.egg-info/SOURCES.txt
chushajo.egg-info/dependency_links.txt
chushajo.egg-info/not-zip-safe
chushajo.egg-info/top_level.txt