Metadata-Version: 1.0
Name: chushajo
Version: 0.1
Summary: Parking API
Home-page: https://github.com/kimi1989/chushajo.git
Author: Kimi Jin
Author-email: jinyinzhen@gmail.com
License: MIT
Platform: UNKNOWN
